{
   "$schema": "./room.schema.json",
   "background": "below",
   "preload": [
      "archiveAssets"
   ],
   "layers": {
      "below": [
         {
            "tags": [
               "mightyrings"
            ],
            "attachments": [
               {
                  "type": "sprite",
                  "frames": [
                     "iooCRing2"
                  ]
               }
            ],
            "position": {
               "x": 720,
               "y": 0
            }
         },
         {
            "barriers": [
               {
                  "position": {
                     "x": 640,
                     "y": 340
                  },
                  "size": {
                     "x": -640,
                     "y": -240
                  }
               },
               {
                  "size": {
                     "x": 700,
                     "y": -20
                  },
                  "position": {
                     "x": 0,
                     "y": 40
                  }
               },
               {
                  "position": {
                     "x": 700,
                     "y": 80
                  },
                  "size": {
                     "x": 260,
                     "y": -40
                  }
               },
               {
                  "position": {
                     "x": 920,
                     "y": 120
                  },
                  "size": {
                     "x": -20,
                     "y": 120
                  }
               },
               {
                  "position": {
                     "x": 700,
                     "y": 340
                  },
                  "size": {
                     "x": 200,
                     "y": -220
                  }
               },
               {
                  "position": {
                     "x": 960,
                     "y": 80
                  },
                  "size": {
                     "x": 20,
                     "y": 160
                  }
               },
               {
                  "position": {
                     "x": 980,
                     "y": 240
                  },
                  "size": {
                     "x": 20,
                     "y": 80
                  }
               },
               {
                  "position": {
                     "x": 900,
                     "y": 320
                  },
                  "size": {
                     "x": 80,
                     "y": 20
                  }
               }
            ],
            "triggers": [
               {
                  "position": {
                     "x": 640,
                     "y": 335
                  },
                  "size": {
                     "x": 60,
                     "y": 20
                  },
                  "name": "teleport",
                  "args": [
                     "c_archive_path2",
                     "down",
                     "830",
                     "10"
                  ]
               },
               {
                  "size": {
                     "x": -20,
                     "y": 60
                  },
                  "position": {
                     "x": 5,
                     "y": 40
                  },
                  "name": "teleport",
                  "args": [
                     "c_archive_path4",
                     "left",
                     "960",
                     "270"
                  ]
               }
            ],
            "interacts": [],
            "position": {
               "x": 0,
               "y": 0
            }
         },
         {
            "tags": [
               "akd"
            ],
            "attachments": [
               {
                  "type": "animation",
                  "resources": "iooCArchiveKeystoneDiamond",
                  "position": {
                     "x": 0,
                     "y": 5
                  },
                  "anchor": {
                     "x": 0,
                     "y": 0
                  }
               },
               {
                  "type": "animation",
                  "position": {
                     "x": 80,
                     "y": 5
                  },
                  "resources": "iooCArchiveKeystoneDiamond",
                  "anchor": {
                     "x": 0,
                     "y": 0
                  }
               }
            ],
            "triggers": [
               {
                  "position": {
                     "x": 0,
                     "y": 60
                  },
                  "size": {
                     "x": 80,
                     "y": 40
                  },
                  "name": "citadel",
                  "args": [
                     "ringzone",
                     "670",
                     "100",
                     "right"
                  ]
               }
            ],
            "position": {
               "x": 800,
               "y": 20
            }
         }
      ],
      "main": [
         {
            "attachments": [
               {
                  "active": true,
                  "type": "animation",
                  "anchor": {
                     "x": 0,
                     "y": 0
                  },
                  "resources": "iooSavePoint",
                  "position": {
                     "y": -10,
                     "x": 0
                  }
               }
            ],
            "interacts": [
               {
                  "name": "save",
                  "position": {
                     "x": -10
                  },
                  "size": {
                     "x": 20,
                     "y": -10
                  }
               }
            ],
            "barriers": [
               {
                  "position": {
                     "x": -10
                  },
                  "size": {
                     "x": 20,
                     "y": -10
                  }
               }
            ],
            "position": {
               "x": 940,
               "y": 300
            },
            "tags": [
               "spawn"
            ]
         },
         {
            "attachments": [
               {
                  "type": "sprite",
                  "frames": [
                     "iooCArchiveLight"
                  ],
                  "anchor": {
                     "x": 0,
                     "y": 0
                  },
                  "position": {
                     "x": 0,
                     "y": 0
                  }
               }
            ],
            "position": {
               "x": 730,
               "y": 340
            },
            "tags": [
               "archiveLight"
            ]
         },
         {
            "attachments": [
               {
                  "type": "sprite",
                  "frames": [
                     "iooCArchiveLight"
                  ],
                  "anchor": {
                     "x": 0,
                     "y": 0
                  },
                  "position": {
                     "x": 0,
                     "y": 0
                  }
               }
            ],
            "position": {
               "x": 1010,
               "y": 280
            },
            "tags": [
               "archiveLight"
            ]
         },
         {
            "attachments": [
               {
                  "type": "sprite",
                  "frames": [
                     "iooCArchiveLight"
                  ],
                  "anchor": {
                     "x": 0,
                     "y": 0
                  },
                  "position": {
                     "x": 0,
                     "y": 0
                  }
               }
            ],
            "position": {
               "x": 870,
               "y": 280
            },
            "tags": [
               "archiveLight"
            ]
         },
         {
            "attachments": [
               {
                  "type": "sprite",
                  "frames": [
                     "iooCArchiveLight"
                  ],
                  "anchor": {
                     "x": 0,
                     "y": 0
                  },
                  "position": {
                     "x": 0,
                     "y": 0
                  }
               }
            ],
            "position": {
               "x": 630,
               "y": -50
            },
            "tags": [
               "archiveLight"
            ]
         },
         {
            "attachments": [
               {
                  "type": "sprite",
                  "frames": [
                     "iooCArchiveLight"
                  ],
                  "anchor": {
                     "x": 0,
                     "y": 0
                  },
                  "position": {
                     "x": 0,
                     "y": 0
                  }
               }
            ],
            "position": {
               "x": 450,
               "y": -50
            },
            "tags": [
               "archiveLight"
            ]
         },
         {
            "attachments": [
               {
                  "type": "sprite",
                  "frames": [
                     "iooCArchiveLight"
                  ],
                  "anchor": {
                     "x": 0,
                     "y": 0
                  },
                  "position": {
                     "x": 0,
                     "y": 0
                  }
               }
            ],
            "position": {
               "x": 270,
               "y": -50
            },
            "tags": [
               "archiveLight"
            ]
         },
         {
            "attachments": [
               {
                  "type": "sprite",
                  "frames": [
                     "iooCArchiveLight"
                  ],
                  "anchor": {
                     "x": 0,
                     "y": 0
                  },
                  "position": {
                     "x": 0,
                     "y": 0
                  }
               }
            ],
            "position": {
               "x": 90,
               "y": -50
            },
            "tags": [
               "archiveLight"
            ]
         },
         {
            "attachments": [
               {
                  "type": "sprite",
                  "frames": [
                     "iooCArchiveLight"
                  ],
                  "anchor": {
                     "x": 0,
                     "y": 0
                  },
                  "position": {
                     "x": 0,
                     "y": 0
                  }
               }
            ],
            "position": {
               "x": 90,
               "y": 190
            },
            "tags": [
               "archiveLight"
            ]
         },
         {
            "attachments": [
               {
                  "type": "sprite",
                  "frames": [
                     "iooCArchiveLight"
                  ],
                  "anchor": {
                     "x": 0,
                     "y": 0
                  },
                  "position": {
                     "x": 0,
                     "y": 0
                  }
               }
            ],
            "position": {
               "x": 270,
               "y": 190
            },
            "tags": [
               "archiveLight"
            ]
         }
      ],
      "above": [
         {
            "tags": [
               "arch"
            ],
            "attachments": [
               {
                  "type": "sprite",
                  "frames": [
                     "iooCArch2"
                  ],
                  "position": {
                     "x": 800,
                     "y": 40
                  }
               },
               {
                  "type": "sprite",
                  "frames": [
                     "iooCArch2"
                  ],
                  "position": {
                     "x": 880,
                     "y": 40
                  }
               }
            ],
            "position": {
               "x": 20,
               "y": -23
            }
         }
      ]
   },
   "neighbors": [
      "c_archive_path2",
      "c_archive_path4",
      "c_archive_foundryA1"
   ],
   "score": {
      "music": "archive",
      "gain": 1
   },
   "region": [
      {
         "x": 160,
         "y": 40
      },
      {
         "x": 880,
         "y": 180
      }
   ],
   "spawn": {
      "x": 940,
      "y": 240
   }
}