{
   "$schema": "./room.schema.json",
   "background": "below",
   "preload": [
      "amGenerator",
      "ionFBird",
      "ionFBirdCry",
      "ionFBirdFly",
      "iocAsrielTrueDownSad",
      "iocAsrielTrueRightSad",
      "iocAsrielTrueLeftSad"
   ],
   "layers": {
      "below": [
         {
            "barriers": [
               {
                  "position": {
                     "x": 0,
                     "y": 160
                  },
                  "size": {
                     "x": 45,
                     "y": -20
                  }
               },
               {
                  "position": {
                     "x": 45,
                     "y": 135
                  },
                  "size": {
                     "x": 5,
                     "y": 20
                  },
                  "anchor": {
                     "x": -1,
                     "y": -1
                  }
               },
               {
                  "position": {
                     "x": 50,
                     "y": 150
                  },
                  "size": {
                     "x": 5,
                     "y": -20
                  }
               },
               {
                  "position": {
                     "x": 60,
                     "y": 125
                  },
                  "size": {
                     "x": -5,
                     "y": 20
                  }
               },
               {
                  "position": {
                     "x": 60,
                     "y": 120
                  },
                  "size": {
                     "x": 5,
                     "y": 20
                  }
               },
               {
                  "position": {
                     "x": 65,
                     "y": 115
                  },
                  "size": {
                     "x": 5,
                     "y": 20
                  }
               },
               {
                  "position": {
                     "x": 75,
                     "y": 110
                  },
                  "size": {
                     "x": -5,
                     "y": 20
                  }
               },
               {
                  "position": {
                     "x": 80,
                     "y": 105
                  },
                  "size": {
                     "x": -5,
                     "y": 20
                  }
               },
               {
                  "position": {
                     "x": 80,
                     "y": 100
                  },
                  "size": {
                     "x": 40,
                     "y": 20
                  }
               },
               {
                  "position": {
                     "x": 120,
                     "y": 100
                  },
                  "size": {
                     "x": 40,
                     "y": -20
                  }
               },
               {
                  "position": {
                     "x": 161,
                     "y": 180
                  },
                  "size": {
                     "x": -40,
                     "y": 20
                  }
               },
               {
                  "position": {
                     "x": 80,
                     "y": 160
                  },
                  "size": {
                     "x": 40,
                     "y": 20
                  }
               },
               {
                  "position": {
                     "x": 75,
                     "y": 170
                  },
                  "size": {
                     "x": -5,
                     "y": 20
                  }
               },
               {
                  "position": {
                     "x": 65,
                     "y": 175
                  },
                  "size": {
                     "x": 5,
                     "y": 20
                  }
               },
               {
                  "position": {
                     "x": 60,
                     "y": 180
                  },
                  "size": {
                     "x": 5,
                     "y": 20
                  }
               },
               {
                  "position": {
                     "x": 60,
                     "y": 185
                  },
                  "size": {
                     "x": -5,
                     "y": 20
                  }
               },
               {
                  "position": {
                     "x": 50,
                     "y": 190
                  },
                  "size": {
                     "x": 5,
                     "y": 20
                  }
               },
               {
                  "position": {
                     "x": 45,
                     "y": 195
                  },
                  "size": {
                     "x": 5,
                     "y": 20
                  }
               },
               {
                  "position": {
                     "x": 80,
                     "y": 165
                  },
                  "size": {
                     "x": -5,
                     "y": 20
                  }
               },
               {
                  "position": {
                     "x": 45,
                     "y": 200
                  },
                  "size": {
                     "x": -45,
                     "y": 20
                  }
               },
               {
                  "position": {
                     "x": 160,
                     "y": 100
                  },
                  "size": {
                     "x": 20,
                     "y": 80
                  }
               },
               {
                  "position": {
                     "x": 1340,
                     "y": 100
                  },
                  "size": {
                     "x": -20,
                     "y": 80
                  }
               }
            ],
            "triggers": [
               {
                  "position": {
                     "x": 5,
                     "y": 160
                  },
                  "size": {
                     "x": -20,
                     "y": 40
                  },
                  "name": "teleport",
                  "args": [
                     "f_telescope",
                     "left",
                     "400",
                     "140"
                  ]
               },
               {
                  "name": "outlands",
                  "position": {
                     "x": 40,
                     "y": 120
                  },
                  "size": {
                     "x": 40,
                     "y": 80
                  },
                  "args": [
                     "x-elevation",
                     "-1",
                     "40",
                     "80"
                  ]
               }
            ]
         },
         {
            "position": {
               "x": 1400,
               "y": 0
            },
            "barriers": [
               {
                  "position": {
                     "x": -60,
                     "y": 100
                  },
                  "size": {
                     "x": 40,
                     "y": -20
                  }
               },
               {
                  "position": {
                     "x": -20,
                     "y": 100
                  },
                  "size": {
                     "x": 40,
                     "y": 20
                  }
               },
               {
                  "position": {
                     "x": 55,
                     "y": 160
                  },
                  "size": {
                     "x": 45,
                     "y": -20
                  }
               },
               {
                  "position": {
                     "x": -60,
                     "y": 180
                  },
                  "size": {
                     "x": 40,
                     "y": 20
                  }
               },
               {
                  "position": {
                     "x": -20,
                     "y": 160
                  },
                  "size": {
                     "x": 40,
                     "y": 20
                  }
               },
               {
                  "position": {
                     "x": 55,
                     "y": 200
                  },
                  "size": {
                     "x": 45,
                     "y": 20
                  }
               },
               {
                  "position": {
                     "x": 20,
                     "y": 105
                  },
                  "size": {
                     "x": 5,
                     "y": 20
                  }
               },
               {
                  "position": {
                     "x": 25,
                     "y": 110
                  },
                  "size": {
                     "x": 5,
                     "y": 20
                  }
               },
               {
                  "position": {
                     "x": 30,
                     "y": 115
                  },
                  "size": {
                     "x": 5,
                     "y": 20
                  }
               },
               {
                  "position": {
                     "x": 40,
                     "y": 120
                  },
                  "size": {
                     "x": -5,
                     "y": 20
                  }
               },
               {
                  "position": {
                     "x": 50,
                     "y": 135
                  },
                  "size": {
                     "x": 5,
                     "y": 20
                  }
               },
               {
                  "position": {
                     "x": 45,
                     "y": 125
                  },
                  "size": {
                     "x": -5,
                     "y": 20
                  }
               },
               {
                  "position": {
                     "x": 50,
                     "y": 130
                  },
                  "size": {
                     "x": -5,
                     "y": 20
                  }
               },
               {
                  "position": {
                     "x": 20,
                     "y": 185
                  },
                  "size": {
                     "x": 5,
                     "y": -20
                  }
               },
               {
                  "position": {
                     "x": 25,
                     "y": 190
                  },
                  "size": {
                     "x": 5,
                     "y": -20
                  }
               },
               {
                  "position": {
                     "x": 35,
                     "y": 175
                  },
                  "size": {
                     "x": -5,
                     "y": 20
                  }
               },
               {
                  "position": {
                     "x": 40,
                     "y": 180
                  },
                  "size": {
                     "x": -5,
                     "y": 20
                  }
               },
               {
                  "position": {
                     "x": 40,
                     "y": 205
                  },
                  "size": {
                     "x": 5,
                     "y": -20
                  }
               },
               {
                  "position": {
                     "x": 45,
                     "y": 210
                  },
                  "size": {
                     "x": 5,
                     "y": -20
                  }
               },
               {
                  "position": {
                     "x": 55,
                     "y": 215
                  },
                  "size": {
                     "x": -5,
                     "y": -20
                  }
               }
            ],
            "triggers": [
               {
                  "position": {
                     "x": 95,
                     "y": 160
                  },
                  "size": {
                     "x": 20,
                     "y": 40
                  },
                  "name": "teleport",
                  "args": [
                     "f_hub",
                     "right",
                     "20",
                     "140"
                  ]
               },
               {
                  "position": {
                     "x": 20,
                     "y": 120
                  },
                  "size": {
                     "x": 40,
                     "y": 80
                  },
                  "name": "outlands",
                  "args": [
                     "x-elevation",
                     "1",
                     "1420",
                     "1460"
                  ]
               }
            ]
         }
      ],
      "main": [
         {
            "attachments": [
               {
                  "type": "animation",
                  "resources": "iooFHovercrystal",
                  "anchor": {
                     "x": 0,
                     "y": 0.25
                  },
                  "active": true
               }
            ],
            "position": {
               "x": 140,
               "y": 80
            },
            "tags": [
               "hovercrystal"
            ]
         },
         {
            "attachments": [
               {
                  "type": "animation",
                  "resources": "iooFHovercrystal",
                  "anchor": {
                     "x": 0,
                     "y": 0.25
                  },
                  "active": true
               }
            ],
            "position": {
               "x": 140,
               "y": 200
            },
            "tags": [
               "hovercrystal"
            ]
         },
         {
            "attachments": [
               {
                  "type": "animation",
                  "resources": "iooFHovercrystal",
                  "anchor": {
                     "x": 0,
                     "y": 0.25
                  },
                  "active": true
               }
            ],
            "position": {
               "x": 1360,
               "y": 80
            },
            "tags": [
               "hovercrystal"
            ]
         },
         {
            "attachments": [
               {
                  "type": "animation",
                  "resources": "iooFHovercrystal",
                  "anchor": {
                     "x": 0,
                     "y": 0.25
                  },
                  "active": true
               }
            ],
            "position": {
               "x": 1360,
               "y": 200
            },
            "tags": [
               "hovercrystal"
            ]
         }
      ],
      "above": []
   },
   "mixins": {
      "above": "foundry-overlay"
   },
   "region": [
      {
         "x": 160,
         "y": 120
      },
      {
         "x": 1340,
         "y": 120
      }
   ],
   "score": {
      "music": "generator",
      "gain": 1
   },
   "neighbors": [
      "f_telescope",
      "f_hub"
   ]
}